YaleKorean/__init__.py
YaleKorean/dict_total.py
YaleKorean/dict_yale.py
YaleKorean/yale.py
YaleKorean-1.0.1.dist-info/LICENSE
YaleKorean-1.0.1.dist-info/METADATA
YaleKorean-1.0.1.dist-info/WHEEL
YaleKorean-1.0.1.dist-info/top_level.txt
YaleKorean-1.0.1.dist-info/RECORD
