Metadata-Version: 2.1
Name: YaleKorean
Version: 1.0.1
Summary: Korean Yale Romanizer
Home-page: https://github.com/SeHaan/YaleKorean
Author: SeHaan
Author-email: alsgk1123@gmail.com
Keywords: Yale,Korean,Romanizer,linguistics,pypi
Classifier: Programming Language :: Python :: 3
Classifier: License :: OSI Approved :: MIT License
Classifier: Operating System :: OS Independent
Requires-Python: >=3.8
License-File: LICENSE
